[
  { "name": "Alert Red Warp Loader Identification Key", "cost": 20000 },
  { "name": "Ballroom Etiquette - Bearing Insult", "cost": 9600 },
  { "name": "Carrots of Passion Orchestrion Roll", "cost": 6000 },
  { "name": "Cosmic Antenna", "cost": 3000 },
  { "name": "Cosmic Circumferbench", "cost": 3000 },
  { "name": "Cosmomodule Flooring", "cost": 4000 },
  { "name": "Cosmomodule Inner Wall", "cost": 4000 },
  { "name": "Cosmic Safety Lamp", "cost": 3000 },
  { "name": "Cosmochair", "cost": 3000 },
  { "name": "Docking Station Cover", "cost": 3000 },
  { "name": "Hey, Cid! Orchestrion Roll", "cost": 6000 },
  { "name": "Interstellar Dhalmel Card", "cost": 4000 },
  { "name": "Interstellar Dhalmel Whistle", "cost": 29000 },
  { "name": "Rapid-fab Vacuum Suit Identification Key", "cost": 20000 },
  { "name": "Shady Cosmoshelter", "cost": 3000 },
  { "name": "Stellar Lamppost", "cost": 3000 },
  { "name": "The Airship Orchestrion Roll", "cost": 6000 },
  { "name": "The Faces We Wear - Ornamented Leather Eyepatch (Left)", "cost": 3000 },
  { "name": "The Faces We Wear - Ornamented Leather Eyepatch (Right)", "cost": 3000 },
  { "name": "The Faces We Wear - Reading Glasses", "cost": 6000 },
  { "name": "Aji Amarillo", "cost": 30 },
  { "name": "Azure Blue Dye", "cost": 600 },
  { "name": "Bright Orange Dye", "cost": 600 },
  { "name": "Canary Yellow Dye", "cost": 600 },
  { "name": "Carmine Red Dye", "cost": 600 },
  { "name": "Cassava", "cost": 30 },
  { "name": "Cherry Pink Dye", "cost": 600 },
  { "name": "Condensed Solution", "cost": 250 },
  { "name": "Crafter's Delineation", "cost": 30 },
  { "name": "Craftsman's Command Materia XII", "cost": 900 },
  { "name": "Craftsman's Command Materia XI", "cost": 450 },
  { "name": "Craftsman's Competence Materia XII", "cost": 900 },
  { "name": "Craftsman's Competence Materia XI", "cost": 450 },
  { "name": "Craftsman's Cunning Materia XII", "cost": 900 },
  { "name": "Craftsman's Cunning Materia XI", "cost": 450 },
  { "name": "Dragonfly", "cost": 10 },
  { "name": "Dragoon Blue Dye", "cost": 600 },
  { "name": "Gatherer's Grasp Materia XII", "cost": 900 },
  { "name": "Gatherer's Grasp Materia XI", "cost": 450 },
  { "name": "Gatherer's Guerdon Materia XII", "cost": 900 },
  { "name": "Gatherer's Guerdon Materia XI", "cost": 450 },
  { "name": "Gatherer's Guile Materia XII", "cost": 900 },
  { "name": "Gatherer's Guile Materia XI", "cost": 450 },
  { "name": "Ghost Nipper", "cost": 10 },
  { "name": "Gunmetal Black Dye", "cost": 1500 },
  { "name": "Hi-Cordial", "cost": 40 },
  { "name": "Levinchrome Aethersand", "cost": 600 },
  { "name": "Mason's Abrasive", "cost": 1000 },
  { "name": "Metallic Brass Dye", "cost": 1500 },
  { "name": "Mythbrine Aethersand", "cost": 400 },
  { "name": "Mythloam Aethersand", "cost": 400 },
  { "name": "Mythroot Aethersand", "cost": 400 },
  { "name": "Neon Green Dye", "cost": 600 },
  { "name": "Neon Pink Dye", "cost": 600 },
  { "name": "Neon Yellow Dye", "cost": 600 },
  { "name": "Pearl White Dye", "cost": 1500 },
  { "name": "Popper Lure", "cost": 100 },
  { "name": "Queso Fresco", "cost": 30 },
  { "name": "Red Maggots", "cost": 10 },
  { "name": "Ruby Red Dye", "cost": 600 },
  { "name": "Shucked Clam", "cost": 10 },
  { "name": "Splendid Mate Leaves", "cost": 30 },
  { "name": "Sungilt Aethersand", "cost": 200 },
  { "name": "Turquoise Blue Dye", "cost": 600 },
  { "name": "Vanilla Yellow Dye", "cost": 600 },
  { "name": "Violet Purple Dye", "cost": 600 },
  { "name": "White Worm", "cost": 10 },
  { "name": "Woolback Loin", "cost": 30 }
]
